RNS/__init__.py
RNS/_version.py
RNS/example.py
example_package_skyguy-0.1.1.dist-info/METADATA
example_package_skyguy-0.1.1.dist-info/WHEEL
example_package_skyguy-0.1.1.dist-info/licenses/LICENSE
example_package_skyguy-0.1.1.dist-info/RECORD
